b2stats/__init__.py
b2stats-0.1.3.dist-info/LICENSE
b2stats-0.1.3.dist-info/METADATA
b2stats-0.1.3.dist-info/WHEEL
b2stats-0.1.3.dist-info/top_level.txt
b2stats-0.1.3.dist-info/RECORD
